{"24.png952681":{"filename":"24.png","size":41298,"regions":[{"shape_attributes":{"name":"polyline","all_points_x":[107,392,898,1344,1946,1995,2008,2009],"all_points_y":[1455,1375,1236,1111,939,919,898,876]},"region_attributes":{"class":""}},{"shape_attributes":{"name":"polyline","all_points_x":[2115,2010],"all_points_y":[837,876]},"region_attributes":{"class":""}},{"shape_attributes":{"name":"polyline","all_points_x":[2015,2143],"all_points_y":[917,866]},"region_attributes":{"class":""}},{"shape_attributes":{"name":"polyline","all_points_x":[2121,2146,2179,2230,2366,2515,2655,2736,3004,3148,3300,3407,3656,3684],"all_points_y":[839,856,855,842,809,749,686,653,584,569,558,544,487,478]},"region_attributes":{"class":""}},{"shape_attributes":{"name":"polyline","all_points_x":[3295,2435],"all_points_y":[575,792]},"region_attributes":{"class":""}},{"shape_attributes":{"name":"polyline","all_points_x":[3571,2792,2379,2096,1640,1177,701,482],"all_points_y":[573,770,877,958,1091,1220,1351,1411]},"region_attributes":{"class":""}},{"shape_attributes":{"name":"polyline","all_points_x":[539,1186,1439,1905,2020,2079,2089],"all_points_y":[1454,1279,1206,1075,1046,1048,1050]},"region_attributes":{"class":""}},{"shape_attributes":{"name":"polyline","all_points_x":[2051,2360],"all_points_y":[1037,956]},"region_attributes":{"class":""}},{"shape_attributes":{"name":"polyline","all_points_x":[2264,2197,2149,2123,2091],"all_points_y":[1454,1263,1115,1071,1050]},"region_attributes":{"class":""}},{"shape_attributes":{"name":"polyline","all_points_x":[2400,2316,2294,2292,2305,2327],"all_points_y":[1453,1220,1136,1066,1022,989]},"region_attributes":{"class":""}},{"shape_attributes":{"name":"polyline","all_points_x":[2308,2198],"all_points_y":[1380,1069]},"region_attributes":{"class":""}},{"shape_attributes":{"name":"polyline","all_points_x":[2136,2286],"all_points_y":[1075,1034]},"region_attributes":{"class":""}},{"shape_attributes":{"name":"polyline","all_points_x":[2308,2103],"all_points_y":[990,1048]},"region_attributes":{"class":""}},{"shape_attributes":{"name":"polyline","all_points_x":[2333,2370,2419,2899,3447,3552,3682],"all_points_y":[985,956,935,813,672,643,608]},"region_attributes":{"class":""}}],"file_attributes":{}}}